autopwn/autopwn.apc
autopwn/__init__.py
autopwn/assessments/nmap-common-ports.apc
autopwn/assessments/nmap.apc
autopwn/assessments/test.apc_
autopwn/assessments/drupal.apc
autopwn/assessments/dir-brute.apc
autopwn/assessments/webapp.apc
autopwn/assessments/example.apc_
autopwn/assessments/unix-audit.apc
autopwn/assessments/nmap-aggressive.apc
autopwn/assessments/udp-scanning.apc
autopwn/assessments/windows-audit.apc
autopwn/assessments/ssl-audit.apc
autopwn/__pycache__/__init__.cpython-34.pyc
autopwn/__pycache__/__init__.cpython-32.pyc
autopwn/tools/nmap-common-ports.apc
autopwn/tools/dirb.apc
autopwn/tools/nmap.apc
autopwn/tools/udp-proto-scanner.apc
autopwn/tools/patator-unzip.apc
autopwn/tools/enum4linux.apc
autopwn/tools/patator-mssql.apc
autopwn/tools/testsslserver.apc
autopwn/tools/msf-scanner-smb-version.apc
autopwn/tools/msf-scanner-smtp-enum.apc
autopwn/tools/patator-keystore.apc
autopwn/tools/httrack.apc
autopwn/tools/showmount.apc
autopwn/tools/snmpcheck.apc
autopwn/tools/scp_to.apc
autopwn/tools/patator-vnc.apc
autopwn/tools/scp_from.apc
autopwn/tools/linux-exploit-suggester.apc
autopwn/tools/unix-privesc-check.apc
autopwn/tools/unix_privesc_check.apc
autopwn/tools/patator-mysql.apc
autopwn/tools/patator-ssh.apc
autopwn/tools/linenum.apc
autopwn/tools/patator-example.apc_
autopwn/tools/example.apc_
autopwn/tools/testssl.apc
autopwn/tools/ssh_execute.apc
autopwn/tools/sslscan.apc
autopwn/tools/nmap-aggressive.apc
autopwn/tools/patator-ftp.apc
autopwn/tools/cmsmap.apc
autopwn/tools/nbtscan.apc
autopwn/tools/sslyze.apc
autopwn/tools/msf-scanner-finger-users.apc
autopwn/tools/arachni.apc
autopwn/tools/hydra.apc
autopwn/tools/nikto.apc
autopwn/tools/skipfish.apc
autopwn/tools/lynis.apc
autopwn/tools/patator-snmp.apc
autopwn-0.25.0.dist-info/metadata.json
autopwn-0.25.0.dist-info/top_level.txt
autopwn-0.25.0.dist-info/DESCRIPTION.rst
autopwn-0.25.0.dist-info/RECORD
autopwn-0.25.0.dist-info/entry_points.txt
autopwn-0.25.0.dist-info/METADATA
autopwn-0.25.0.dist-info/WHEEL
