Metadata-Version: 2.0
Name: autopwn
Version: 0.25.0
Summary: Specify targets and run sets of tools against them
Home-page: https://github.com/nccgroup/autopwn
Author: Aidan Marlin
Author-email: aidan.marlin@nccgroup.trust
License: GNU Affero GPL v3
Keywords: autopwn pentest automate toolset hack
Platform: UNKNOWN
Classifier: Programming Language :: Python :: 3
Classifier: Intended Audience :: Information Technology
Classifier: Topic :: Security
Classifier: Environment :: Console
Requires-Dist: PyYAML
Requires-Dist: screenutils
Requires-Dist: inquirer
Requires-Dist: readchar (<=0.7)
